{"stats":{"minecraft:picked_up":{"minecraft:diamond_axe":6,"minecraft:cobblestone":427,"minecraft:flint":1,"minecraft:bucket":4,"minecraft:leather":14,"minecraft:bone":3,"minecraft:gold_nugget":52,"minecraft:diamond_shovel":6,"minecraft:stone_pickaxe":9,"minecraft:diamond":67,"minecraft:iron_sword":1,"minecraft:salmon":7,"minecraft:stick":48,"minecraft:diamond_boots":6,"minecraft:stone_shovel":2,"minecraft:arrow":6,"minecraft:iron_axe":1,"minecraft:iron_ingot":31,"minecraft:raw_iron":6,"minecraft:cobbled_deepslate":727,"minecraft:diamond_chestplate":6,"minecraft:stone_sword":2,"minecraft:stone_axe":2,"minecraft:dandelion":3,"minecraft:lava_bucket":1,"minecraft:mutton":1,"minecraft:diamond_leggings":5,"minecraft:netherrack":29,"minecraft:dirt":153,"minecraft:diamond_helmet":6,"minecraft:gravel":105,"minecraft:diamond_pickaxe":5,"minecraft:tuff":162,"minecraft:leaf_litter":32,"minecraft:oak_log":2,"minecraft:wheat_seeds":44,"minecraft:shield":6,"minecraft:iron_pickaxe":3,"minecraft:pumpkin":39,"minecraft:diamond_sword":5,"minecraft:cooked_beef":16,"minecraft:white_wool":3,"minecraft:flint_and_steel":5,"minecraft:crafting_table":1,"minecraft:rotten_flesh":20,"minecraft:beef":6,"minecraft:apple":1,"minecraft:string":14,"minecraft:golden_sword":15,"minecraft:obsidian":25,"minecraft:cornflower":6},"minecraft:mined":{"minecraft:tall_grass":14,"minecraft:dirt":53,"minecraft:pumpkin":9,"minecraft:netherrack":78,"minecraft:grass_block":23,"minecraft:cobblestone":3,"minecraft:white_wool":1,"minecraft:short_grass":32,"minecraft:tuff":27,"minecraft:diamond_ore":4,"minecraft:deepslate":162,"minecraft:deepslate_diamond_ore":36,"minecraft:crafting_table":1,"minecraft:leaf_litter":2,"minecraft:oak_log":2,"minecraft:obsidian":26,"minecraft:iron_ore":3,"minecraft:stone":92},"minecraft:used":{"minecraft:stone_axe":44,"minecraft:cobbled_deepslate":10,"minecraft:apple":1,"minecraft:shield":24,"minecraft:iron_pickaxe":250,"minecraft:diamond_sword":123,"minecraft:diamond_shovel":5,"minecraft:stone_shovel":62,"minecraft:pumpkin":4,"minecraft:rotten_flesh":7,"minecraft:water_bucket":4,"minecraft:diamond_pickaxe":134,"minecraft:golden_sword":6,"minecraft:salmon":2,"minecraft:furnace":1,"minecraft:mutton":1,"minecraft:dirt":9,"minecraft:obsidian":24,"minecraft:stone_sword":63,"minecraft:lava_bucket":6,"minecraft:diamond_leggings":1,"minecraft:white_wool":1,"minecraft:cobblestone":8,"minecraft:cooked_beef":11,"minecraft:diamond_axe":7,"minecraft:flint_and_steel":1,"minecraft:bucket":11,"minecraft:crafting_table":2,"minecraft:beef":6,"minecraft:stone_pickaxe":56,"minecraft:ender_pearl":1,"minecraft:diamond_boots":1},"minecraft:killed":{"minecraft:salmon":6,"minecraft:zombie":2,"minecraft:zombified_piglin":17,"minecraft:skeleton":1,"minecraft:sheep":1,"minecraft:iron_golem":1,"minecraft:cow":3,"minecraft:piglin":1,"minecraft:villager":4,"minecraft:spider":2},"minecraft:custom":{"minecraft:talked_to_villager":1,"minecraft:time_since_rest":388,"minecraft:leave_game":2,"minecraft:damage_taken":3577,"minecraft:mob_kills":38,"minecraft:time_since_death":352,"minecraft:interact_with_furnace":4,"minecraft:sleep_in_bed":1,"minecraft:total_world_time":111723,"minecraft:swim_one_cm":11597,"minecraft:crouch_one_cm":13992,"minecraft:deaths":9,"minecraft:player_kills":7,"minecraft:damage_blocked_by_shield":2904,"minecraft:interact_with_crafting_table":10,"minecraft:walk_one_cm":168673,"minecraft:walk_under_water_one_cm":6733,"minecraft:play_time":111723,"minecraft:damage_dealt":8556,"minecraft:jump":1180,"minecraft:drop":23,"minecraft:sprint_one_cm":125148,"minecraft:open_chest":3,"minecraft:fall_one_cm":37523,"minecraft:fly_one_cm":171585,"minecraft:walk_on_water_one_cm":8211,"minecraft:sneak_time":6465},"minecraft:broken":{"minecraft:golden_sword":1,"minecraft:iron_pickaxe":1},"minecraft:crafted":{"minecraft:flint_and_steel":1,"minecraft:bucket":1,"minecraft:furnace":1,"minecraft:diamond_boots":1,"minecraft:iron_ingot":3,"minecraft:diamond_shovel":1,"minecraft:diamond_helmet":1,"minecraft:crafting_table":1,"minecraft:diamond_leggings":1,"minecraft:stick":20,"minecraft:shield":1,"minecraft:oak_planks":8,"minecraft:diamond_axe":1,"minecraft:diamond_pickaxe":2,"minecraft:diamond_chestplate":1,"minecraft:iron_pickaxe":2,"minecraft:diamond_sword":1,"minecraft:air":0},"minecraft:dropped":{"minecraft:iron_axe":1,"minecraft:salmon":4,"minecraft:iron_ingot":15,"minecraft:iron_pickaxe":2,"minecraft:iron_sword":1},"minecraft:killed_by":{"minecraft:player":5,"minecraft:zombie":1}},"DataVersion":4556}